fincept_terminal-2.0.8.dist-info/METADATA
fincept_terminal-2.0.8.dist-info/WHEEL
fincept_terminal-2.0.8.dist-info/entry_points.txt
fincept_terminal-2.0.8.dist-info/licenses/LICENSE
fincept_terminal/Analytics/advanced_search_index.faiss
fincept_terminal/Analytics/advanced_search_index_data.pkl
fincept_terminal/Analytics/data.csv
fincept_terminal/Analytics/data_no_duplicates.csv
fincept_terminal/Analytics/dupl.py
fincept_terminal/Analytics/ext.py
fincept_terminal/Analytics/pyportfolioOpt_wrapper.py
fincept_terminal/Analytics/riskfoliolib_wrapper.py
fincept_terminal/Analytics/skfolio_wrapper.py
fincept_terminal/Brokers/India/angelone/angelone_tab.py
fincept_terminal/Brokers/India/dhan/dhan_tab.py
fincept_terminal/Brokers/India/fyers/fyers_tab.py
fincept_terminal/Brokers/India/zerodha/zerodha_tab.py
fincept_terminal/Brokers/UnitedStates/alpaca/alpaca_tab.py
fincept_terminal/DashBoard/AnalyticsTab/analytics_tab.py
fincept_terminal/DashBoard/AnalyticsTab/data_viewer_tab.py
fincept_terminal/DashBoard/AnalyticsTab/oecd_data_tab.py
fincept_terminal/DashBoard/ChatTab/chat_tab.py
fincept_terminal/DashBoard/DBnomicsTab/dbnomics_tab.py
fincept_terminal/DashBoard/DashboardTab/dashboard_tab.py
fincept_terminal/DashBoard/DatabaseTab/data_access_tab.py
fincept_terminal/DashBoard/DatabaseTab/database_tab.py
fincept_terminal/DashBoard/EquityResearchTab/consumer_behaviour_tab.py
fincept_terminal/DashBoard/EquityResearchTab/yfdata.py
fincept_terminal/DashBoard/ForumTab/forum_tab.py
fincept_terminal/DashBoard/GeoPoliticsTab/geo.py
fincept_terminal/DashBoard/InfoTab/rss_tab.py
fincept_terminal/DashBoard/InfoTab/wiki_tab.py
fincept_terminal/DashBoard/MarineTrackerTab/leaflet_map_ui.py
fincept_terminal/DashBoard/MarineTrackerTab/maps_tab.py
fincept_terminal/DashBoard/MarketTab/market_tab.py
fincept_terminal/DashBoard/NewsAnalysisTab/news_analysis_tab.py
fincept_terminal/DashBoard/PortfolioTab/portfolio_business.py
fincept_terminal/DashBoard/PortfolioTab/portfolio_optimizer.py
fincept_terminal/DashBoard/PortfolioTab/portfolio_tab.py
fincept_terminal/DashBoard/ProfileTab/profile_tab.py
fincept_terminal/DashBoard/RoboAdvisorTab/robo_advisor_tab.py
fincept_terminal-2.0.8.dist-info/RECORD
