Metadata-Version: 2.1
Name: fincept-terminal
Version: 2.0.8
Summary: A Terminal for Financial Market Analysis and Fetching all kinds of Data.
Author-Email: Fincept Corporation <dev@fincept.in>
License: MIT
Classifier: Programming Language :: Python :: 3
Classifier: Operating System :: OS Independent
Requires-Python: <3.14,>=3.11
Requires-Dist: Pillow==11.2.1
Requires-Dist: PyPDF2==2.12.1
Requires-Dist: PyQt5==5.15.11
Requires-Dist: datagovindia==1.0.2
Requires-Dist: dearpygui==2.0.0
Requires-Dist: feedparser==6.0.11
Requires-Dist: fyers_apiv3==3.1.4
Requires-Dist: numpy==2.2.6
Requires-Dist: pandas==2.2.3
Requires-Dist: psutil==7.0.0
Requires-Dist: psycopg2==2.9.10
Requires-Dist: pyotp==2.9.0
Requires-Dist: requests==2.31.0
Requires-Dist: scholarly==1.7.11
Requires-Dist: scipy==1.15.3
Requires-Dist: ta==0.11.0
Requires-Dist: uuid==1.30
Requires-Dist: wikipedia==1.4.0
Requires-Dist: yfinance==0.2.61
Requires-Dist: duckdb==1.3.2
